metap/__init__.py
metap/errors_warns.py
metap/metap.py
metap/macros/default_defs.py
metap/macros/default_impl.py
metap/macros/gen_defaults.py
metap/macros/gen_lib.py
metap/macros/rt_lib.py
metap-0.0.4.dist-info/LICENSE
metap-0.0.4.dist-info/METADATA
metap-0.0.4.dist-info/NOTICE
metap-0.0.4.dist-info/WHEEL
metap-0.0.4.dist-info/top_level.txt
metap-0.0.4.dist-info/RECORD
