Metadata-Version: 2.1
Name: metap
Version: 0.0.4
Summary: A simple meta-programming layer for Python
Author-email: Stefanos Baziotis <stefanos.baziotis@gmail.com>
Project-URL: Homepage, https://github.com/baziotis/metap
Project-URL: Repository, https://github.com/baziotis/metap
Keywords: meta-programming,debugging
Classifier: Development Status :: 3 - Alpha
Classifier: Intended Audience :: Developers
Classifier: Intended Audience :: Science/Research
Classifier: Programming Language :: Python
Classifier: Programming Language :: Python :: 3 :: Only
Classifier: Programming Language :: Python :: 3
Classifier: Programming Language :: Python :: 3.8
Classifier: Programming Language :: Python :: 3.9
Classifier: Programming Language :: Python :: 3.10
Classifier: Programming Language :: Python :: 3.11
Classifier: Programming Language :: Python :: 3.12
Classifier: Operating System :: OS Independent
Classifier: License :: OSI Approved :: Apache Software License
Requires-Python: >=3.8
License-File: LICENSE
License-File: NOTICE
